LICENSE
MANIFEST.in
README.md
setup.py
iccad_contest/__init__.py
iccad_contest/abstract_optimizer.py
iccad_contest/design_space_exploration.py
iccad_contest/version.py
iccad_contest.egg-info/PKG-INFO
iccad_contest.egg-info/SOURCES.txt
iccad_contest.egg-info/dependency_links.txt
iccad_contest.egg-info/requires.txt
iccad_contest.egg-info/top_level.txt
iccad_contest/contest-dataset/__init__.py
iccad_contest/contest-dataset/contest.csv
iccad_contest/contest-dataset/design-space.xlsx
iccad_contest/functions/__init__.py
iccad_contest/functions/dataset.py
iccad_contest/functions/design_space.py
iccad_contest/functions/hypervolume.py
iccad_contest/functions/problem.py
iccad_contest/utils/__init__.py
iccad_contest/utils/arguments.py
iccad_contest/utils/basic_utils.py
iccad_contest/utils/constants.py
iccad_contest/utils/numpy_utils.py
iccad_contest/utils/path_utils.py
iccad_contest/utils/serialize.py
requirements/base.in
requirements/ipynb.in
requirements/optimizers.in