Metadata-Version: 2.1
Name: iccad-contest
Version: 0.0.7
Summary: ICCAD'22 Contest @ Microarchitecture Design Space Exploration
Home-page: https://code.aone.alibaba-inc.com/ctl-research/iccad-contest-platform
Author: Chen BAI
Author-email: baichen.bai@alibaba-inc.com
License: Apache v2
Platform: any
Provides-Extra: optimizers
Provides-Extra: notebooks
License-File: LICENSE
